hlang/__init__.py
hlang/documents/__init__.py
hlang/documents/document.py
hlang/documents/key_value_document.py
hlang/documents/simple_document.py
hlang/embedders/__init__.py
hlang/embedders/embedder.py
hlang/embedders/sentence_transformer_embedder.py
hlang/generators/__init__.py
hlang/generators/aopenai_generator.py
hlang/generators/configs.py
hlang/generators/generator.py
hlang/generators/hf_chat_generator.py
hlang/generators/hf_llm_generator.py
hlang/generators/openai_generator.py
hlang/openai_lazy_client.py
hlang/templates/__init__.py
hlang/templates/chat_prompt_template.py
hlang/types_/__init__.py
hlang/types_/message.py
hlang/vectordb/__init__.py
hlang/vectordb/vector_db.py
hlang-0.2.2.dist-info/LICENSE
hlang-0.2.2.dist-info/METADATA
hlang-0.2.2.dist-info/WHEEL
hlang-0.2.2.dist-info/RECORD
