Metadata-Version: 2.1
Name: hlang
Version: 0.2.2
Summary: 
Author: avmametev
Author-email: mametevalex@gmail.com
Requires-Python: >=3.11,<4.0
Classifier: Programming Language :: Python :: 3
Classifier: Programming Language :: Python :: 3.11
Classifier: Programming Language :: Python :: 3.12
Requires-Dist: chromadb (>=0.5.5,<0.6.0)
Requires-Dist: jinja2 (>=3.1.4,<4.0.0)
Requires-Dist: openai (>=1.40.2,<2.0.0)
Requires-Dist: sentence-transformers (>=3.0.1,<4.0.0)
Requires-Dist: torch (>=2.4.0,<3.0.0)
